{"bugs":[{"cf_status_b2g_2_1_s":"---","blocks":[583242,667980,630007,659188,679966,702183],"cf_status_firefox44":"---","is_cc_accessible":true,"cf_tracking_b2g":"---","keywords":["privacy","productization","productwanted","sec-want","ux-tone"],"cf_qa_whiteboard":"","url":"","qa_contact":"","cf_status_b2g_2_2r":"---","cf_rank":null,"cf_status_firefox45":"---","cf_fx_iteration":"---","cf_tracking_firefox_relnote":"---","cf_last_resolved":"2012-06-15T20:03:48Z","cf_fx_points":"---","cc_detail":[{"email":"aaron.train@gmail.com","real_name":"Aaron Train [:aaronmt]","name":"aaron.train@gmail.com","id":299942},{"email":"afowler@mozilla.com","real_name":"Alex Fowler","name":"afowler@mozilla.com","id":403220},{"email":"ally@mozilla.com","real_name":"Allison Naaktgeboren :ally","name":"ally@mozilla.com","id":384312},{"email":"antoine.mozilla@gmail.com","real_name":"Antoine Turmel [:GeekShadow]","name":"antoine.mozilla@gmail.com","id":333996},{"email":"arendsf@gmail.com","real_name":"Thomas Arend [:tarend]","name":"arendsf@gmail.com","id":399537},{"email":"arun@accosted.net","real_name":"Arun Raghavan","name":"arun@accosted.net","id":124462},{"email":"blassey.bugs@lassey.us","real_name":"Brad Lassey [:blassey] (use needinfo?)","name":"blassey.bugs@lassey.us","id":181004},{"email":"bugzilla@johnath.com","real_name":"Johnathan Nightingale [:johnath]","name":"bugzilla@johnath.com","id":210757},{"email":"bzcc@fowlsmurf.net","real_name":"James May [:fowl]","name":"bzcc@fowlsmurf.net","id":317549},{"email":"isandu@mozilla.com","real_name":"Irina Sandu","name":"isandu@mozilla.com","id":363398},{"email":"jfu@mozilla.com","real_name":"Jaclyn Fu","name":"jfu@mozilla.com","id":383990},{"email":"jruderman@gmail.com","real_name":"Jesse Ruderman","name":"jruderman@gmail.com","id":11608},{"email":"mark.finkle@gmail.com","real_name":"Mark Finkle (:mfinkle)","name":"mark.finkle@gmail.com","id":252194},{"email":"matjk7@gmail.com","real_name":"Matheus Kerschbaum","name":"matjk7@gmail.com","id":383067},{"email":"me@tomlowenthal.com","real_name":"Tom Lowenthal [:StrangeCharm]","name":"me@tomlowenthal.com","id":411898},{"email":"mluna@mozilla.com","real_name":"Michelle Luna","name":"mluna@mozilla.com","id":419442},{"email":"mounir@lamouri.fr","real_name":"Mounir Lamouri (:mounir)","name":"mounir@lamouri.fr","id":342786},{"email":"pwd.mozilla@yahoo.co.uk","real_name":"Paul [pwd]","name":"pwd.mozilla@yahoo.co.uk","id":369453},{"email":"robert.pollak@mykolab.com","real_name":"Robert Pollak","name":"robert.pollak@mykolab.com","id":25874}],"cf_status_firefox42":"---","cf_tracking_win":"---","summary":"Explain how Firefox uses permissions in Android Market description","cf_user_story":"","platform":"All","votes":0,"version":"Trunk","cf_blocking_fx":"---","cf_tracking_p11":"---","mentors_detail":[],"is_creator_accessible":true,"is_confirmed":true,"priority":"P2","assigned_to_detail":{"email":"jfu@mozilla.com","real_name":"Jaclyn Fu","name":"jfu@mozilla.com","id":383990},"creator":"mbrubeck@mozilla.com","cf_blocking_b2g":"---","last_change_time":"2013-07-31T00:02:22Z","cf_tracking_firefox45":"---","cf_status_b2g_2_2":"---","creator_detail":{"email":"mbrubeck@mozilla.com","real_name":"Matt Brubeck (:mbrubeck)","name":"mbrubeck@mozilla.com","id":24045},"cc":["aaron.train@gmail.com","afowler@mozilla.com","ally@mozilla.com","antoine.mozilla@gmail.com","arendsf@gmail.com","arun@accosted.net","blassey.bugs@lassey.us","bugzilla@johnath.com","bzcc@fowlsmurf.net","isandu@mozilla.com","jfu@mozilla.com","jruderman@gmail.com","mark.finkle@gmail.com","matjk7@gmail.com","me@tomlowenthal.com","mluna@mozilla.com","mounir@lamouri.fr","pwd.mozilla@yahoo.co.uk","robert.pollak@mykolab.com"],"assigned_to":"jfu@mozilla.com","groups":[],"see_also":["https://bugzilla.mozilla.org/show_bug.cgi?id=669166"],"id":672352,"whiteboard":"[sg:want][no-code]","creation_time":"2011-07-18T21:14:46Z","cf_blocking_fennec10":"-","depends_on":[691054,751930,751944,857730],"cf_tracking_firefox_esr38":"---","cf_status_firefox_esr38":"---","cf_status_b2g_2_1":"---","mentors":[],"cf_tracking_firefox42":"---","dupe_of":null,"cf_status_b2g_master":"---","resolution":"FIXED","classification":"Client Software","alias":null,"cf_tracking_firefox44":"---","op_sys":"Android","cf_blocking_fennec":"+","status":"RESOLVED","cf_status_b2g_2_0":"---","cf_tracking_firefox43":"---","cf_status_b2g_2_5":"---","cf_status_b2g_2_0m":"---","cf_crash_signature":"","is_open":false,"severity":"normal","cf_status_firefox43":"---","cf_tracking_relnote_b2g":"---","flags":[],"component":"General","target_milestone":"Firefox 11","product":"Firefox for Android"}]}