{"bugs":[{"cf_status_b2g_2_1_s":"---","blocks":[854627,865789,885333,899557,1038557,839838,875018,875289,875299,876397,879245,882076,915233,939909,1035060],"cf_status_firefox44":"---","is_cc_accessible":true,"cf_tracking_b2g":"---","keywords":["dev-doc-needed"],"cf_qa_whiteboard":"","url":"http://dom.spec.whatwg.org/#promises","qa_contact":"","cf_status_b2g_2_2r":"---","cf_rank":null,"cf_status_firefox45":"---","cf_fx_iteration":"---","cf_tracking_firefox_relnote":"---","cf_last_resolved":"2013-06-13T09:39:58Z","cf_fx_points":"---","cf_tracking_thunderbird_esr38":"---","cc_detail":[{"email":"airpingu@gmail.com","real_name":"Gene Lian [:gene] (I already quit Mozilla)","name":"airpingu@gmail.com","id":440330},{"email":"allstars.chh@mozilla.com","real_name":"Yoshi Huang[:allstars.chh]","name":"allstars.chh@mozilla.com","id":434672},{"email":"amarchesini@mozilla.com","real_name":"Andrea Marchesini (:baku)","name":"amarchesini@mozilla.com","id":446257},{"email":"annevk@annevk.nl","real_name":"Anne (:annevk)","name":"annevk@annevk.nl","id":102998},{"email":"bezaleel360@gmail.com","real_name":"ElevenReds","name":"bezaleel360@gmail.com","id":420570},{"email":"bruant.d@gmail.com","real_name":"David Bruant","name":"bruant.d@gmail.com","id":365126},{"email":"brunoaiss@gmail.com","real_name":"brunoais","name":"brunoaiss@gmail.com","id":399973},{"email":"bugmail@asutherland.org","real_name":"Andrew Sutherland [:asuth]","name":"bugmail@asutherland.org","id":151407},{"email":"bugs@pettay.fi","real_name":"Olli Pettay [:smaug]","name":"bugs@pettay.fi","id":39966},{"email":"bugzilla@flaki.hu","real_name":"Szmozsánszky István [:flaki]","name":"bugzilla@flaki.hu","id":449932},{"email":"bugzilla@nulltxt.se","real_name":"David Dahl :ddahl","name":"bugzilla@nulltxt.se","id":335003},{"email":"bzbarsky@mit.edu","real_name":"Boris Zbarsky [:bz]","name":"bzbarsky@mit.edu","id":20209},{"email":"d@domenic.me","real_name":"Domenic Denicola","name":"d@domenic.me","id":308714},{"email":"dherman@mozilla.com","real_name":"Dave Herman [:dherman]","name":"dherman@mozilla.com","id":368424},{"email":"dteller@mozilla.com","real_name":"David Rajchenbach-Teller [:Yoric] (use \"needinfo\")","name":"dteller@mozilla.com","id":181388},{"email":"fb+mozdev@quantumedia.de","real_name":"Florian Bender","name":"fb+mozdev@quantumedia.de","id":413779},{"email":"ferjmoreno@gmail.com","real_name":"Fernando Jiménez Moreno [:ferjm]","name":"ferjmoreno@gmail.com","id":427036},{"email":"gavin.sharp@gmail.com","real_name":":Gavin Sharp [email: gavin@gavinsharp.com]","name":"gavin.sharp@gmail.com","id":103593},{"email":"htsai@mozilla.com","real_name":"Hsin-Yi Tsai [:hsinyi]","name":"htsai@mozilla.com","id":434964},{"email":"jaoo@jaoo.es","real_name":"José Antonio Olivera Ortega [:jaoo]","name":"jaoo@jaoo.es","id":428783},{"email":"jonas@sicking.cc","real_name":"Jonas Sicking (:sicking)","name":"jonas@sicking.cc","id":9186},{"email":"jsmith@mozilla.com","real_name":"Jason Smith [:jsmith]","name":"jsmith@mozilla.com","id":432443},{"email":"laurent@xulfr.org","real_name":"Laurent Jouanneau","name":"laurent@xulfr.org","id":53700},{"email":"markh@mozilla.com","real_name":"Mark Hammond [:markh]","name":"markh@mozilla.com","id":16943},{"email":"mike@w3.org","real_name":"Michael[tm] Smith","name":"mike@w3.org","id":319983},{"email":"mounir@lamouri.fr","real_name":"Mounir Lamouri (:mounir)","name":"mounir@lamouri.fr","id":342786},{"email":"nsm.nikhil@gmail.com","real_name":"Nikhil Marathe [:nsm] (No longer reading bugmail, please needinfo?)","name":"nsm.nikhil@gmail.com","id":415061},{"email":"past@mozilla.com","real_name":"Panos Astithas [:past]","name":"past@mozilla.com","id":363318},{"email":"philringnalda@gmail.com","real_name":"Phil Ringnalda (:philor)","name":"philringnalda@gmail.com","id":135518},{"email":"pivisko@gmail.com","real_name":"Ivan Vadovic","name":"pivisko@gmail.com","id":101275},{"email":"ryou@mozilla.com","real_name":"Rui You [:ryou]","name":"ryou@mozilla.com","id":455100},{"email":"samth@ccs.neu.edu","real_name":"Sam Tobin-Hochstadt [:samth]","name":"samth@ccs.neu.edu","id":265320},{"email":"saneyuki.s.snyk@gmail.com","real_name":"Tetsuharu OHZEKI [UTC+9]","name":"saneyuki.s.snyk@gmail.com","id":360522},{"email":"sankha93@gmail.com","real_name":"Sankha Narayan Guria [:sankha93]","name":"sankha93@gmail.com","id":378359},{"email":"smacleod@mozilla.com","real_name":"Steven MacLeod [:smacleod]","name":"smacleod@mozilla.com","id":460415},{"email":"sonny.piers@gmail.com","real_name":"Sonny Piers [:sonny]","name":"sonny.piers@gmail.com","id":325572},{"email":"sotaro.ikeda.g@gmail.com","real_name":"Sotaro Ikeda [:sotaro]","name":"sotaro.ikeda.g@gmail.com","id":434202},{"email":"syoichi@outlook.com","real_name":"Syoichi Tsuyuhara","name":"syoichi@outlook.com","id":448618},{"email":"teramako@gmail.com","real_name":"teramako","name":"teramako@gmail.com","id":312990},{"email":"ttaubert@mozilla.com","real_name":"Tim Taubert [:ttaubert]","name":"ttaubert@mozilla.com","id":402526},{"email":"vic99999@yandex.ru","real_name":"4esn0k","name":"vic99999@yandex.ru","id":422233},{"email":"xhva.net@gmail.com","real_name":"Andrew Stibbard","name":"xhva.net@gmail.com","id":53986},{"email":"xyuan@mozilla.com","real_name":"Yuan Xulei [:yxl] (Leave from  May 18)","name":"xyuan@mozilla.com","id":430084}],"cf_status_firefox42":"---","summary":"Implement promises","cf_has_str":"---","cf_user_story":"","platform":"All","votes":3,"cf_tracking_e10s":"---","version":"Trunk","cf_blocking_fx":"---","cf_tracking_p11":"---","mentors_detail":[],"cf_feature_b2g":"---","is_creator_accessible":true,"is_confirmed":true,"priority":"--","assigned_to_detail":{"email":"amarchesini@mozilla.com","real_name":"Andrea Marchesini (:baku)","name":"amarchesini@mozilla.com","id":446257},"creator":"annevk@annevk.nl","cf_blocking_b2g":"---","last_change_time":"2014-07-15T06:49:06Z","cf_tracking_firefox45":"---","cf_status_b2g_2_2":"---","creator_detail":{"email":"annevk@annevk.nl","real_name":"Anne (:annevk)","name":"annevk@annevk.nl","id":102998},"cc":["airpingu@gmail.com","allstars.chh@mozilla.com","amarchesini@mozilla.com","annevk@annevk.nl","bezaleel360@gmail.com","bruant.d@gmail.com","brunoaiss@gmail.com","bugmail@asutherland.org","bugs@pettay.fi","bugzilla@flaki.hu","bugzilla@nulltxt.se","bzbarsky@mit.edu","d@domenic.me","dherman@mozilla.com","dteller@mozilla.com","fb+mozdev@quantumedia.de","ferjmoreno@gmail.com","gavin.sharp@gmail.com","htsai@mozilla.com","jaoo@jaoo.es","jonas@sicking.cc","jsmith@mozilla.com","laurent@xulfr.org","markh@mozilla.com","mike@w3.org","mounir@lamouri.fr","nsm.nikhil@gmail.com","past@mozilla.com","philringnalda@gmail.com","pivisko@gmail.com","ryou@mozilla.com","samth@ccs.neu.edu","saneyuki.s.snyk@gmail.com","sankha93@gmail.com","smacleod@mozilla.com","sonny.piers@gmail.com","sotaro.ikeda.g@gmail.com","syoichi@outlook.com","teramako@gmail.com","ttaubert@mozilla.com","vic99999@yandex.ru","xhva.net@gmail.com","xyuan@mozilla.com"],"assigned_to":"amarchesini@mozilla.com","groups":[],"see_also":["https://bugs.webkit.org/show_bug.cgi?id=113571"],"id":856410,"whiteboard":"[Async]","creation_time":"2013-03-31T13:03:23Z","depends_on":[878849,956343,883683,887687,897913,904143,939906,942255,958684,1008467,1009569,1013625],"cf_tracking_firefox_esr38":"---","cf_status_firefox_esr38":"---","cf_status_b2g_2_1":"---","mentors":[],"cf_tracking_firefox42":"---","dupe_of":null,"cf_status_b2g_master":"---","resolution":"FIXED","classification":"Components","cf_has_regression_range":"---","alias":"promises","cf_tracking_firefox44":"---","op_sys":"All","cf_blocking_fennec":"---","status":"RESOLVED","cf_status_b2g_2_0":"---","cf_tracking_firefox43":"---","cf_status_b2g_2_5":"---","cf_status_b2g_2_0m":"---","cf_crash_signature":"","is_open":false,"cf_status_firefox43":"---","severity":"normal","cf_tracking_relnote_b2g":"---","flags":[{"modification_date":"2013-06-12T01:43:46Z","creation_date":"2013-06-12T01:43:46Z","type_id":37,"status":"+","name":"in-testsuite","id":662766,"setter":"ryanvm@gmail.com"}],"component":"DOM","target_milestone":"mozilla24","product":"Core","cf_status_thunderbird_esr38":"---"}]}